bedrock_usage_analyzer/__init__.py
bedrock_usage_analyzer/__main__.py
bedrock_usage_analyzer/aws/__init__.py
bedrock_usage_analyzer/aws/bedrock.py
bedrock_usage_analyzer/aws/bedrock_llm.py
bedrock_usage_analyzer/aws/servicequotas.py
bedrock_usage_analyzer/aws/sts.py
bedrock_usage_analyzer/core/__init__.py
bedrock_usage_analyzer/core/analyzer.py
bedrock_usage_analyzer/core/metrics_fetcher.py
bedrock_usage_analyzer/core/output_generator.py
bedrock_usage_analyzer/core/profile_fetcher.py
bedrock_usage_analyzer/core/user_inputs.py
bedrock_usage_analyzer/metadata/__init__.py
bedrock_usage_analyzer/metadata/fm-list-af-south-1.yml
bedrock_usage_analyzer/metadata/fm-list-ap-east-2.yml
bedrock_usage_analyzer/metadata/fm-list-ap-northeast-1.yml
bedrock_usage_analyzer/metadata/fm-list-ap-northeast-2.yml
bedrock_usage_analyzer/metadata/fm-list-ap-northeast-3.yml
bedrock_usage_analyzer/metadata/fm-list-ap-south-1.yml
bedrock_usage_analyzer/metadata/fm-list-ap-south-2.yml
bedrock_usage_analyzer/metadata/fm-list-ap-southeast-1.yml
bedrock_usage_analyzer/metadata/fm-list-ap-southeast-2.yml
bedrock_usage_analyzer/metadata/fm-list-ap-southeast-3.yml
bedrock_usage_analyzer/metadata/fm-list-ap-southeast-4.yml
bedrock_usage_analyzer/metadata/fm-list-ap-southeast-5.yml
bedrock_usage_analyzer/metadata/fm-list-ap-southeast-6.yml
bedrock_usage_analyzer/metadata/fm-list-ap-southeast-7.yml
bedrock_usage_analyzer/metadata/fm-list-ca-central-1.yml
bedrock_usage_analyzer/metadata/fm-list-ca-west-1.yml
bedrock_usage_analyzer/metadata/fm-list-eu-central-1.yml
bedrock_usage_analyzer/metadata/fm-list-eu-central-2.yml
bedrock_usage_analyzer/metadata/fm-list-eu-north-1.yml
bedrock_usage_analyzer/metadata/fm-list-eu-south-1.yml
bedrock_usage_analyzer/metadata/fm-list-eu-west-1.yml
bedrock_usage_analyzer/metadata/fm-list-eu-west-2.yml
bedrock_usage_analyzer/metadata/fm-list-eu-west-3.yml
bedrock_usage_analyzer/metadata/fm-list-me-central-1.yml
bedrock_usage_analyzer/metadata/fm-list-me-south-1.yml
bedrock_usage_analyzer-0.5.0b0.dist-info/licenses/LICENSE
bedrock_usage_analyzer-0.5.0b0.dist-info/licenses/NOTICE
bedrock_usage_analyzer-0.5.0b0.dist-info/METADATA
bedrock_usage_analyzer-0.5.0b0.dist-info/WHEEL
bedrock_usage_analyzer-0.5.0b0.dist-info/entry_points.txt
bedrock_usage_analyzer-0.5.0b0.dist-info/top_level.txt
bedrock_usage_analyzer-0.5.0b0.dist-info/RECORD
