Metadata-Version: 2.4
Name: bedrock-usage-analyzer
Version: 0.5.0b0
Summary: Calculate token usage statistics and map quotas for Amazon Bedrock models
Author: Amazon Web Services
License-Expression: Apache-2.0
Project-URL: Repository, https://github.com/awslabs/bedrock-usage-analyzer
Keywords: aws,bedrock,cloudwatch,metrics,tokens,usage,statistics
Requires-Python: >=3.9
License-File: LICENSE
License-File: NOTICE
Requires-Dist: boto3
Requires-Dist: numpy
Requires-Dist: jinja2
Requires-Dist: pyyaml
Requires-Dist: defusedcsv
Requires-Dist: platformdirs
Dynamic: license-file
